# Lambda表达式被编译成了什么

> 先进行总结，方便回顾：
>
> - 编译时
>
>   - Lambda表达式会在当前的声明类中生成一个私有静态方法， 方法实现了Lambda表达式的代码逻辑
>
> - - 生成invokedynamic指令， 调用bootstrap methods， 由java.lang.invoke.LambdaMetafactory.metafactory方法实现
>
> - 运行时
>
> - - invokedynamic指令调用metafactory方法。它会返回一个CallSite, 此CallSite返回目标类型的一个匿名实现类， 此类内部关联编译时生成的私有静态方法
>   - lambda表达式进行传递时，传递的是生成的内部类实例。

## 一个简单的例子

```java
public class LambdaTest {
    public static final LambdaTest lambdaTest = new LambdaTest();
    public String getName() {
        return "9627";
    }
    public static void main(String[] args) {
        Function<?, String> functionDemo = s -> LambdaTest.lambdaTest.getName();
    }
}
```

使用命令编译 javac -g LambdaTest.java   （此时并没有生成内部类class文件）

使用命令查看字节码 javap -v -p LambdaTest.class	（编译的文件过大，已屏蔽掉干扰信息，只关注lambda相关信息）

```java
public static void main(java.lang.String[]);
    descriptor: ([Ljava/lang/String;)V
    flags: ACC_PUBLIC, ACC_STATIC
    Code:
      stack=1, locals=2, args_size=1
         0: invokedynamic #6,  0              // InvokeDynamic #0:apply:()Ljava/util/function/Function;
         5: astore_1
         6: return

private static java.lang.String lambda$main$0(java.lang.Object);
    descriptor: (Ljava/lang/Object;)Ljava/lang/String;
    flags: ACC_PRIVATE, ACC_STATIC, ACC_SYNTHETIC
    Code:
      stack=1, locals=1, args_size=1
         0: getstatic     #7                  // Field lambdaTest:Lsuishen/redis/hash/mapping/test/LambdaTest;
         3: invokevirtual #8                  // Method getName:()Ljava/lang/String;
         6: areturn
         
BootstrapMethods:
  0: #46 invokestatic java/lang/invoke/LambdaMetafactory.metafactory:(此处方法签名描述省略)
    Method arguments:
      #47 (Ljava/lang/Object;)Ljava/lang/Object;
      #48 invokestatic suishen/redis/hash/mapping/test/LambdaTest.lambda$main$0:(Ljava/lang/Object;)Ljava/lang/String;
      #49 (Ljava/lang/Object;)Ljava/lang/String;
```

### invokedynamic 指令

可以看到例子中的lambda表达式   `s -> LambdaTest.lambdaTest.getName()` 编译后生成了 invokedynamic 指令，`#6`定位到常量池中下面的记录。

​			*#6 = InvokeDynamic      #0:#50         // #0:apply:()Ljava/util/function/Function;*

其中 `#0` 指向的 BootstrapMethods 区的静态工厂方法   `java.lang.invoke.LambdaMetafactory.metafactory`

LambdaMetafactory.metafactory()方法会利用asm字节码框架为 lambda表达式生成内部类，底层细节，此处不做深究。

### 私有静态方法

编译后的class多了一个私有静态方法， LambdaTest.lambda$main$0(Object),尝试将字节码翻译成java代码，如下：

```java
private static java.lang.String lambda$main$0(Object o) {
		return LambdaTest.LambdaTest.getName();
}
```

方法逻辑跟栗子中的lambda逻辑一致。

编译期间未看到生成的相关内部类。

## 运行Lambda

执行命令 **java -Djdk.internal.lambda.dumpProxyClasses TestLambda** 

运行结束后会在同级目录生成一个内部类的class文件   **LambdaTest$$Lambda$1.class**

使用命令查看内部类的字节码 **javap -v -p LambdaTest$$Lambda$1.class**，也可以在idea中直接打开查看，此处直观的展示了idea反编译后的内容

```java
final class LambdaTest$$Lambda$1 implements Function {
    private LambdaTest$$Lambda$1() {
    }
  
    @Hidden
    public Object apply(Object var1) {
        return LambdaTest.lambda$main$0(var1);
    }
}
```

简单分析下：

1、该内部类类名 LambdaTest$$Lambda$1，

2、实现了函数式接口Function 的apply方法，

3、方法内部调用的上文提到的，该内部类所在的声明类，编译后所生成的私有静态方法。LambdaTest.lambda$main$0(Object)



到这，就可以把lambda运行逻辑串联起来了。

- 编译时lambda表达式会在当前声明类，生成一个私有静态方法，该方法逻辑与lambda逻辑相同。
- 运行时动态的使用asm字节码工具生成一个实现了目标函数式接口的内部类。
- 内部类进行实例化，方法间传递的是内部类的实例
- 调用内部类实例的函数式接口方法（SAM Single Abstract Method）
- 内部继续调用了声明类的私有静态方法，执行我们编写的真正的lambda表达式逻辑

## 捕获变量的例子

在匿名内部类中调用外部参数时，参数必须声明为final。

Lambda表达式内也可以引用上下文中的变量，称之为捕获变量、捕获参数。

Lambda表达式内捕获的外部变量，可以不声明为final类型，但是上下文语义中必须等同与final，也就是在后续逻辑中不可修改。

同样的一个简单的例子，lambda表达式 `s -> lambdaTest.getName()`捕获了上下文中的变量 lambdaTest。

```java
public class LambdaTest {
    public String getName() {
        return "9627";
    }
    public static void main(String[] args) {
        LambdaTest lambdaTest = new LambdaTest();
        Function<?, String> functionDemo = s -> lambdaTest.getName();
    }
}
```

使用命令编译 javac -g LambdaTest.java

使用命令查看字节码 javap -v -p LambdaTest.class

```java
public static void main(java.lang.String[]);
    descriptor: ([Ljava/lang/String;)V
    flags: ACC_PUBLIC, ACC_STATIC
    Code:
      stack=2, locals=3, args_size=1
         0: new           #6                  // class suishen/redis/hash/mapping/test/LambdaTest
         3: dup
         4: invokespecial #7                  // Method "<init>":()V
         7: astore_1
         8: aload_1
         9: invokedynamic #8,  0              // InvokeDynamic #0:apply:(Lsuishen/redis/hash/mapping/test/LambdaTest;)Ljava/util/function/Function;
        14: astore_2
        15: return

private static java.lang.String lambda$main$0(suishen.redis.hash.mapping.test.LambdaTest, java.lang.Object);
    descriptor: (Lsuishen/redis/hash/mapping/test/LambdaTest;Ljava/lang/Object;)Ljava/lang/String;
    flags: ACC_PRIVATE, ACC_STATIC, ACC_SYNTHETIC
    Code:
      stack=1, locals=2, args_size=2
         0: aload_0
         1: invokevirtual #9                  // Method getName:()Ljava/lang/String;
         4: areturn
BootstrapMethods:
  0: #45 invokestatic java/lang/invoke/LambdaMetafactory.metafactory:(此处方法签名描述省略)
    Method arguments:
      #46 (Ljava/lang/Object;)Ljava/lang/Object;
      #47 invokestatic suishen/redis/hash/mapping/test/LambdaTest.lambda$main$0:(Lsuishen/redis/hash/mapping/test/LambdaTest;Ljava/lang/Object;)Ljava/lang/String;
      #48 (Ljava/lang/Object;)Ljava/lang/String;
```

### 私有静态方法

尝试将字节码翻译成java代码，看下区别在哪里。

```java
private static java.lang.String lambda$main$0(LambdaTest lambdaTest, Object o) {
		return lambdaTest.getName();
}
```

方法逻辑跟栗子中的lambda逻辑一致。但是方法参数多了一个LambdaTest lambdaTest。

### 内部类

执行命令 **java -Djdk.internal.lambda.dumpProxyClasses TestLambda** 

使用命令查看内部类的字节码 **javap -v -p LambdaTest.class**，也可以在idea中直接打开查看，此处直观的展示了idea反编译后的内容

```java
final class LambdaTest$$Lambda$1 implements Function {
    private final LambdaTest arg$1;

    private LambdaTest$$Lambda$1(LambdaTest var1) {
        this.arg$1 = var1;
    }

    private static Function get$Lambda(LambdaTest var0) {
        return new LambdaTest$$Lambda$1(var0);
    }

    @Hidden
    public Object apply(Object var1) {
        return LambdaTest.lambda$main$0(this.arg$1, var1);
    }
}
```

简单分析下：

1、该内部类类名 LambdaTest$$Lambda$1，

2、实现了函数式接口Function 的apply方法，

3、内置了一个**Field private final LambdaTest arg$1** 这个实例属性在运行期动态调用，进行内部类实例化时，捕获自声明类上下文中的变量

4、函数式接口方法内部调用的上文提到的私有静态方法，同时传入捕获的变量。前后呼应。



梳理下存在捕获变量的lambda流程：

- 编译时lambda表达式会在当前声明类，生成一个私有静态方法，该方法逻辑与lambda逻辑相同。如果lambda表达式有捕获变量，则方法会多出与对应类型的参数。
- 运行时动态的使用asm字节码工具生成一个实现了目标函数式接口的内部类。如果lambda表达式有捕获变量，则内部类中会多出与之对应的属性。（***此处大胆假设，因为不管执行多少次，生成的内部类class都是一样的，所以运行时应该会优化成只执行一次***）
- 内部类进行实例化，方法间传递的是内部类的实例。（***此处大胆假设，因为捕获了上下文中的变量，而这个变量在运行时是变化的，不确定的，所以每次调用都生成的新的内部类实例***）
- 调用内部类实例的函数式接口方法（SAM Single Abstract Method）
- 内部继续调用了声明类的私有静态方法，执行我们编写的真正的lambda表达式逻辑

## 重复的Lambda表达式

### 多个长得一样的lambda表达式

```java
public static void main(String[] args) {
    LambdaTest lambdaTest = new LambdaTest();
    Function<?, String> functionDemo = s -> lambdaTest.getName();
    Function<?, String> functionDemo1 = s -> lambdaTest.getName();
}
```

- 编译后会生成两个invokedynamic命令，两个私有静态方法

- 运行时会生成两个内部类class

### 循环同一个lambda表达式

```java
public static void main(String[] args) {
    LambdaTest lambdaTest = new LambdaTest();
    for (int i = 0; i < 10; i++) {
        Function<?, String> functionDemo = s -> lambdaTest.getName();
    }
}
```

- 编译后会生成一个invokedynamic命令，一个私有静态方法

- 运行时会生成一个内部类class

## 测试生成的实例是否相同

### 不存在捕获变量

```java
public final static LambdaTest lambdaTest = new LambdaTest();
public static void main(String[] args) {
    LambdaTest lambdaTest = LambdaTest.lambdaTest;
    for (int i = 0; i < 5; i++) {
        Function<?, String> functionDemo = s -> LambdaTest.lambdaTest.getName();
        System.out.println(functionDemo);
    }
}
打印信息：
suishen.redis.hash.mapping.test.LambdaTest$$Lambda$1/1973336893@4cdf35a9
suishen.redis.hash.mapping.test.LambdaTest$$Lambda$1/1973336893@4cdf35a9
suishen.redis.hash.mapping.test.LambdaTest$$Lambda$1/1973336893@4cdf35a9
suishen.redis.hash.mapping.test.LambdaTest$$Lambda$1/1973336893@4cdf35a9
suishen.redis.hash.mapping.test.LambdaTest$$Lambda$1/1973336893@4cdf35a9
```

生成的实例是相同的。

### 存在捕获变量

```java
public final static LambdaTest lambdaTest = new LambdaTest();
public static void main(String[] args) {
    LambdaTest lambdaTest = new LambdaTest();
    for (int i = 0; i < 5; i++) {
        Function<?, String> functionDemo = s -> lambdaTest.getName();
        System.out.println(functionDemo);
    }
}
打印信息：
suishen.redis.hash.mapping.test.LambdaTest$$Lambda$1/1973336893@45fe3ee3
suishen.redis.hash.mapping.test.LambdaTest$$Lambda$1/1973336893@4cdf35a9
suishen.redis.hash.mapping.test.LambdaTest$$Lambda$1/1973336893@4c98385c
suishen.redis.hash.mapping.test.LambdaTest$$Lambda$1/1973336893@5fcfe4b2
suishen.redis.hash.mapping.test.LambdaTest$$Lambda$1/1973336893@6bf2d08e
```

生成的实例是不同的

### 存在捕获变量，捕获变量是类的静态属性

```java
public final static LambdaTest lambdaTest = new LambdaTest();
public static void main(String[] args) {
    LambdaTest lambdaTest = LambdaTest.lambdaTest;
    for (int i = 0; i < 5; i++) {
        Function<?, String> functionDemo = s -> lambdaTest.getName();
        System.out.println(functionDemo);
    }
}
打印信息：
suishen.redis.hash.mapping.test.LambdaTest$$Lambda$1/1973336893@45fe3ee3
suishen.redis.hash.mapping.test.LambdaTest$$Lambda$1/1973336893@4cdf35a9
suishen.redis.hash.mapping.test.LambdaTest$$Lambda$1/1973336893@4c98385c
suishen.redis.hash.mapping.test.LambdaTest$$Lambda$1/1973336893@5fcfe4b2
suishen.redis.hash.mapping.test.LambdaTest$$Lambda$1/1973336893@6bf2d08e
```

生成的实例是不同的

### 总结：

- 如果不存在捕获变量，每次调用生成的实例是相同的
- 如果存在捕获变量，每次调用生成的实例是不相同的

与猜想一致，以上。

> *来自网络*
>
> # Lambda表达式的转换策略
>
> Brian Goetz是Oracle的Java语言架构师， JSR 335(Lambda Expression)规范的lead, 写了几篇Lambda设计方面的文章， 其中之一就是Translation of Lambda Expressions。这篇文章介绍了Java 8 Lambda设计时的考虑以及实现方法。
>
> 他提到， Lambda表达式可以通过内部类， method handle, dynamic proxy等方式实现， 但是这些方法各有优劣。真正要实现Lambda表达式， 必须兼顾两个目标：一是不引入特定策略，以期为将来的优化提供最大的灵活性， 二是保持类文件格式的稳定。通过Java 7中引入的**invokedynamic** （JSR 292）, 可以很好的兼顾这两个目标。
>
> **invokedynamic** 在缺乏静态类型信息的情况下可以支持有效的灵活的方法调用。主要是为了日益增长的运行在JVM上的动态类型语言， 如Groovy, JRuby。
>
> **invokedynamic** 将Lambda表达式的转换策略推迟到运行时， 这也意味着我们现在编译的代码在将来的转换策略改变的情况下也能正常运行。
>
> 编译器在编译的时候， 会将Lambda表达式的表达式体 (lambda body)脱糖(desugar) 成一个方法，此方法的参数列表和返回类型和lambda表达式一致， 如果有捕获参数， 脱糖的方法的参数可能会更多一些， 并会产生一个**invokedynamic**调用， 调用一个call site。（如果是一个方法引用的话，会进行不一样的处理，不会脱糖成静态方法，而是将方法调用写入了生成的内部类中）
>
> 这个call site被调用时会返回lambda表达式的目标类型(functional interface)的一个实现类。这个call site称为这个lambda表达式的*lambda factory*。 *lambda factory*的bootstrap方法是一个标准方法， 叫做*lambda metafactory*。
>
> 编译器在转换lambda表达式时， 可以推断出表达式的参数类型，返回类型以及异常， 称之为`natural signature`， 我们将目标类型的方法签名称之为`lambda descriptor`, lambda factory的返回对象实现了函数式接口， 并且关联的表达式的代码逻辑， 称之为`lambda object`。





