# 方法引用被编译成了什么

> 先进行总结，方便回顾：
>
> lambda表达式同方法引用编译之后的基本一致，区别在于：
>
> - lambda表达式会在声明类中生成私有静态方法，lambda表达式的业务逻辑也在其中
> - 方法引用不会生成私有静态方法，引用的方法在动态生成的内部类中调用

有了之前编译lambda表达式的例子，这次废话不多说，直接开始。

## 一个简单的例子

```java
public class LambdaTest {
    public String getName() {
        return "9627";
    }
    public static void main(String[] args) {
        Function<LambdaTest, String> functionDemo = LambdaTest::getName;
    }
}
```

使用命令编译 javac -g LambdaTest.java

使用命令查看字节码 javap -v -p LambdaTest.class

```java
public static void main(java.lang.String[]);
    descriptor: ([Ljava/lang/String;)V
    flags: ACC_PUBLIC, ACC_STATIC
    Code:
      stack=1, locals=2, args_size=1
         0: invokedynamic #6,  0              // InvokeDynamic #0:apply:()Ljava/util/function/Function;
         5: astore_1
         6: return

BootstrapMethods:
  0: #41 invokestatic java/lang/invoke/LambdaMetafactory.metafactory:
    Method arguments:
      #42 (Ljava/lang/Object;)Ljava/lang/Object;
      #43 invokevirtual suishen/redis/hash/mapping/test/LambdaTest.getName:()Ljava/lang/String;
      #44 (Lsuishen/redis/hash/mapping/test/LambdaTest;)Ljava/lang/String;
```

编译之后invokedynamic 指令跟之前编译lambda表达式一致，但是没有生成私有静态方法。

运行下看看生成的内部类：

执行命令 **java -Djdk.internal.lambda.dumpProxyClasses TestLambda** 

使用命令查看内部类的字节码 **javap -v -p LambdaTest$$Lambda$1.class**

```java
final class LambdaTest$$Lambda$1 implements Function {
    private LambdaTest$$Lambda$1() {
    }

    @Hidden
    public Object apply(Object var1) {
        return ((LambdaTest)var1).getName();
    }
}
```

简单分析下：

1、该内部类类名 LambdaTest$$Lambda$1

2、实现了函数式接口Function 的apply方法

3、apply方法内部对传入的参数进行强制类型转换，必须是LambdaTest类型的，符合预期

3、apply方法内部调用了，LambdaTest实例的getName()方法，LambdaTest实例来自调用方传入

## 捕获变量的例子

```java
public class LambdaTest {
    public Long toLong(String name) {
        return 9527L;
    }
    public static void main(String[] args) {
        LambdaTest lambdaTest = new LambdaTest();
        Function<String, Long> functionDemo = lambdaTest::toLong;
    }
```

```java
 public static void main(java.lang.String[]);
    descriptor: ([Ljava/lang/String;)V
    flags: ACC_PUBLIC, ACC_STATIC
    Code:
      stack=2, locals=2, args_size=1
         0: getstatic     #6                  // Field lambdaTest:Lsuishen/redis/hash/mapping/test/LambdaTest;
         3: dup
         4: invokevirtual #7                  // Method java/lang/Object.getClass:()Ljava/lang/Class;
         7: pop
         8: invokedynamic #8,  0              // InvokeDynamic #0:apply:(Lsuishen/redis/hash/mapping/test/LambdaTest;)Ljava/util/function/Function;
        13: astore_1
        14: return
BootstrapMethods:
  0: #44 invokestatic java/lang/invoke/LambdaMetafactory.metafactory:
    Method arguments:
      #45 (Ljava/lang/Object;)Ljava/lang/Object;
      #46 invokevirtual suishen/redis/hash/mapping/test/LambdaTest.toLong:(Ljava/lang/String;)Ljava/lang/Long;
      #47 (Ljava/lang/String;)Ljava/lang/Long;
```

```java
final class LambdaTest$$Lambda$1 implements Function {
    private final LambdaTest arg$1;
    private LambdaTest$$Lambda$1(LambdaTest var1) {
        this.arg$1 = var1;
    }
    private static Function get$Lambda(LambdaTest var0) {
        return new LambdaTest$$Lambda$1(var0);
    }
    @Hidden
    public Object apply(Object var1) {
        return this.arg$1.toLong((String)var1);
    }
}
```

我们只关注下最终生成的内部类，简单分析下：

1、该内部类类名 LambdaTest$$Lambda$1，

2、实现了函数式接口Function 的apply方法

3、内置了一个**Field private final LambdaTest arg$1** 这个实例属性在运行期动态调用，进行内部类实例化时，捕获自声明类上下文中的变量

4、apply方法内部调用了，arg$1.toLong(String)，参数来自调用方传入

### 总结：

#### 1、lambda表达式同方法引用编译之后的基本一致，区别在于：

- lambda表达式会在声明类中生成私有静态方法，lambda表达式的业务逻辑也在其中
- 方法引用不会生成私有静态方法，引用的方法在动态生成的内部类中调用

#### 2、方法引用、方法引用，主体是方法，已经定义好的方法，逻辑都在方法中，下游逻辑只管调用就好了。这也算是区别于lambda表达式地方吧（逻辑代码块 {code....} ），所以lambda表达式的代码块在编译期中原封不动的放在了生成的私有静态方法中，也算是有所归属。感觉像是编译期人为的向方法引用靠拢，以期在运行期动态调用时达成共性的逻辑（啊这一大段纯属猜测，看个乐，觉得有用，就当是抛砖引玉了）

- 不存在捕获变量：没有对象实体，下游逻辑传入对象实例，调用方法。
- 存在捕获变量：存在对象实体，下游逻辑传入方法所需参数，调用方法。

## 疑问-胡天扯地

```java
private final static LambdaTest lambdaTest = new LambdaTest();
LambdaTest.lambdaTest::toLong
```

LambdaTest.lambdaTest 是私有静态属性，类似这样的方法引用也是存在捕获变量的，意味着每次调用都会生成一个新的内部类实例，但是此时捕获的变量 LambdaTest.lambdaTest 是不可变的。

个人觉得此种情况可以不用捕获变量，生成的内部类中，直接在方法体中嵌入这个对象，每次调用也不用生成新的内部类实例。

**一**是我草率了，因为毕竟是猜测，在我的知识盲区，可能有不能这么处理的原因。

**二**是官方目前没做优化，但是将来可能会对这种情况有优化？毕竟动态调用模式非常灵活，jvm内部的策略升级对我们是透明无感知的。





